{
  "fetched_at": "2026-07-01T08:39:11.978659+05:30",
  "rates": {
    "sampath": {
      "USD": 331.75,
      "GBP": 437.4543,
      "EUR": 375.9877,
      "JPY": 2.0263,
      "AUD": 226.4283,
      "NZD": 186.7335,
      "CHF": 407.3504,
      "SEK": 33.8807,
      "DKK": 50.3007,
      "CAD": 231.8663,
      "SGD": 254.4652,
      "HKD": 42.0355,
      "NOK": 33.1818,
      "CNY": 48.5366,
      "ZAR": 20.0729,
      "AED": 89.7726,
      "INR": 3.4826
    },
    "hnb": {
      "AUD": 227.1419,
      "GBP": 439.5914,
      "CAD": 232.9722,
      "CNY": 48.9275,
      "DKK": 50.3419,
      "EUR": 378.111,
      "HKD": 42.2012,
      "INR": 3.399,
      "JPY": 2.0477,
      "NZD": 186.4879,
      "NOK": 32.8337,
      "SGD": 256.0263,
      "SEK": 33.5905,
      "CHF": 408.697,
      "THB": 9.4112,
      "AED": 90.0195,
      "USD": 332.5
    },
    "peoples": {
      "USD": 330.4332,
      "JPY": 2.036,
      "GBP": 438.0743,
      "EUR": 376.1327,
      "AUD": 224.868,
      "THB": 9.9906,
      "SGD": 256.4377,
      "SEK": 33.9589,
      "SAR": 88.5999,
      "QAR": 91.366,
      "OMR": 864.6765,
      "NZD": 187.0861,
      "NOK": 33.2351,
      "MYR": 81.4105,
      "KWD": 1081.1546,
      "JOD": 469.5169,
      "INR": 3.4643,
      "HKD": 42.248,
      "DKK": 50.3646,
      "CNY": 48.5216,
      "CHF": 409.5845,
      "CAD": 232.7121,
      "BHD": 882.9907,
      "AED": 90.6408
    },
    "ndb": {
      "AUD": 224.53,
      "BHD": 0.0,
      "CAD": 231.45,
      "CNY": 48.13,
      "DKK": 49.83,
      "EUR": 376.46,
      "HKD": 42.14,
      "INR": 3.5,
      "JPY": 2.0365,
      "KWD": 0.0,
      "NZD": 185.65,
      "NOK": 33.02,
      "OMR": 0.0,
      "SAR": 86.07,
      "SGD": 254.4,
      "GBP": 437.3,
      "SEK": 33.74,
      "CHF": 407.48,
      "THB": 0.0,
      "AED": 89.11,
      "USD": 331.75
    }
  }
}